setfield/__init__.py
tests/__init__.py
tests/test_setfield.py
django_postgres_setfield-0.0.1.dist-info/LICENSE
django_postgres_setfield-0.0.1.dist-info/METADATA
django_postgres_setfield-0.0.1.dist-info/WHEEL
django_postgres_setfield-0.0.1.dist-info/top_level.txt
django_postgres_setfield-0.0.1.dist-info/RECORD
